cij/__init__.py
cij/version.py
cij/cli/__init__.py
cij/cli/cij.py
cij/cli/extract.py
cij/cli/fill.py
cij/cli/geotherm.py
cij/cli/main.py
cij/cli/modes.py
cij/cli/plot.py
cij/cli/static.py
cij/core/__init__.py
cij/core/calculator.py
cij/core/full_modulus.py
cij/core/mode_gamma.py
cij/core/modulus_worker.py
cij/core/qha_adapter.py
cij/core/tasks.py
cij/core/phonon_contribution/__init__.py
cij/core/phonon_contribution/nonshear.py
cij/core/phonon_contribution/shear.py
cij/data/__init__.py
cij/data/constraints/cubic
cij/data/constraints/hexagonal
cij/data/constraints/monoclinic
cij/data/constraints/orthorhombic
cij/data/constraints/tetragonal6
cij/data/constraints/tetragonal7
cij/data/constraints/triclinic
cij/data/constraints/trigonal6
cij/data/constraints/trigonal7
cij/data/default/settings.yaml
cij/data/output/writer_rules.yml
cij/data/schema/config.schema.json
cij/io/__init__.py
cij/io/config/__init__.py
cij/io/config/config.py
cij/io/config/validate.py
cij/io/output/__init__.py
cij/io/output/results_writer.py
cij/io/traditional/__init__.py
cij/io/traditional/elast_dat.py
cij/io/traditional/models.py
cij/io/traditional/qha_input.py
cij/io/traditional/qha_output.py
cij/misc/__init__.py
cij/misc/eig_sort_freqs.py
cij/misc/evec_disp2eig.py
cij/misc/evec_load.py
cij/misc/evec_sort.py
cij/plot/__init__.py
cij/plot/color_map.py
cij/plot/modes.py
cij/plot/plotter.py
cij/plot/pvticker.py
cij/plot/quick.py
cij/plot/tasks.py
cij/util/__init__.py
cij/util/compliance.py
cij/util/fill.py
cij/util/static_eos.py
cij/util/units.py
cij/util/voigt.py
cij-1.0.0b4.dist-info/LICENCE
cij-1.0.0b4.dist-info/METADATA
cij-1.0.0b4.dist-info/WHEEL
cij-1.0.0b4.dist-info/entry_points.txt
cij-1.0.0b4.dist-info/top_level.txt
cij-1.0.0b4.dist-info/RECORD
