Metadata-Version: 2.1
Name: cij
Version: 1.0.0b4
Summary: High temperature thermal elasticity
Home-page: https://github.com/MineralsCloud/cij/
Author: Chenxing Luo
Author-email: chenxing.luo@columbia.edu
License-File: LICENCE
Requires-Dist: numpy >=1.10.0
Requires-Dist: pandas
Requires-Dist: scipy
Requires-Dist: qha
Requires-Dist: lazy-property
Requires-Dist: pint >=0.10
Requires-Dist: networkx
Requires-Dist: click
Requires-Dist: jsonschema
Requires-Dist: sympy
